streamjoy/.gitignore
streamjoy/__init__.py
streamjoy/_utils.py
streamjoy/cli.py
streamjoy/core.py
streamjoy/models.py
streamjoy/pandas.py
streamjoy/polars.py
streamjoy/renderers.py
streamjoy/serializers.py
streamjoy/settings.py
streamjoy/streams.py
streamjoy/ui.py
streamjoy/wrappers.py
streamjoy/xarray.py
streamjoy-0.0.10.dist-info/METADATA
streamjoy-0.0.10.dist-info/WHEEL
streamjoy-0.0.10.dist-info/entry_points.txt
streamjoy-0.0.10.dist-info/licenses/LICENSE
streamjoy-0.0.10.dist-info/RECORD
