Metadata-Version: 2.3
Name: streamjoy
Version: 0.0.10
Summary: Enjoy animating images into GIFs and MP4s!
Project-URL: Documentation, https://ahuang11.github.io/streamjoy/
Project-URL: Source, https://github.com/ahuang11/streamjoy
Author-email: streamjoy <hey.at.py@gmail.com>
License-File: LICENSE
Classifier: Programming Language :: Python :: 3 :: Only
Requires-Python: >=3.9
Requires-Dist: bs4
Requires-Dist: dask[distributed]
Requires-Dist: imageio[pyav]>=2.34.0
Requires-Dist: param>2
Requires-Dist: pygifsicle==1.0.5
Requires-Dist: requests
Provides-Extra: ui
Requires-Dist: netcdf4; extra == 'ui'
Requires-Dist: panel; extra == 'ui'
Requires-Dist: param; extra == 'ui'
Requires-Dist: requests; extra == 'ui'
Requires-Dist: xarray; extra == 'ui'
